tests/__init__.py
tests/conftest.py
tests/test_constants.py
tests/test_encryption.py
tests/test_sdk.py
yagoutpay/__init__.py
yagoutpay/constants.py
yagoutpay/direct_api.py
yagoutpay/dynamic_link.py
yagoutpay/encryption.py
yagoutpay/hosted_checkout.py
yagoutpay/sdk.py
yagoutpay/static_link.py
yagoutpay_sdk-0.1.0.dist-info/METADATA
yagoutpay_sdk-0.1.0.dist-info/WHEEL
yagoutpay_sdk-0.1.0.dist-info/top_level.txt
yagoutpay_sdk-0.1.0.dist-info/RECORD
